lavendertown/__init__.py
lavendertown/cli.py
lavendertown/cli_typer.py
lavendertown/config.py
lavendertown/inspector.py
lavendertown/logging_config.py
lavendertown/models.py
lavendertown/profiling.py
lavendertown/collaboration/__init__.py
lavendertown/collaboration/api.py
lavendertown/collaboration/database_storage.py
lavendertown/collaboration/models.py
lavendertown/collaboration/storage.py
lavendertown/detectors/__init__.py
lavendertown/detectors/base.py
lavendertown/detectors/changepoint.py
lavendertown/detectors/ml_anomaly.py
lavendertown/detectors/null.py
lavendertown/detectors/outlier.py
lavendertown/detectors/rule_based.py
lavendertown/detectors/timeseries.py
lavendertown/detectors/timeseries_features.py
lavendertown/detectors/type.py
lavendertown/drift/__init__.py
lavendertown/drift/compare.py
lavendertown/drift/distribution.py
lavendertown/drift/schema.py
lavendertown/export/__init__.py
lavendertown/export/csv.py
lavendertown/export/great_expectations.py
lavendertown/export/json.py
lavendertown/export/pandera.py
lavendertown/export/parquet.py
lavendertown/rules/__init__.py
lavendertown/rules/base.py
lavendertown/rules/cross_column.py
lavendertown/rules/executors.py
lavendertown/rules/models.py
lavendertown/rules/storage.py
lavendertown/ui/__init__.py
lavendertown/ui/base.py
lavendertown/ui/charts.py
lavendertown/ui/collaboration.py
lavendertown/ui/export.py
lavendertown/ui/extras.py
lavendertown/ui/layout.py
lavendertown/ui/overview.py
lavendertown/ui/rules.py
lavendertown/ui/sidebar.py
lavendertown/ui/table.py
lavendertown/ui/upload.py
lavendertown/ui/visualizations/__init__.py
lavendertown/ui/visualizations/altair_backend.py
lavendertown/ui/visualizations/base.py
lavendertown/ui/visualizations/plotly_backend.py
lavendertown/ui/visualizations/plotly_charts.py
lavendertown/utils/__init__.py
lavendertown/utils/faker_helpers.py
lavendertown-0.7.1.dist-info/METADATA
lavendertown-0.7.1.dist-info/WHEEL
lavendertown-0.7.1.dist-info/entry_points.txt
lavendertown-0.7.1.dist-info/licenses/LICENSE
lavendertown-0.7.1.dist-info/RECORD
