Metadata-Version: 2.4
Name: lavendertown
Version: 0.7.1
Summary: A Streamlit-first Python package for detecting and visualizing data quality issues
Project-URL: Homepage, https://github.com/eddiethedean/lavendertown
Project-URL: Repository, https://github.com/eddiethedean/lavendertown
Project-URL: Issues, https://github.com/eddiethedean/lavendertown/issues
Author-email: Odos Matthews <odosmatthews@gmail.com>
License: MIT
License-File: LICENSE
Keywords: data-profiling,data-quality,data-validation,streamlit
Classifier: Development Status :: 3 - Alpha
Classifier: Intended Audience :: Developers
Classifier: License :: OSI Approved :: MIT License
Classifier: Programming Language :: Python :: 3
Classifier: Programming Language :: Python :: 3.10
Classifier: Programming Language :: Python :: 3.11
Classifier: Programming Language :: Python :: 3.12
Requires-Python: >=3.10
Requires-Dist: altair>=4.2.1
Requires-Dist: click>=8.0.0
Requires-Dist: pandas>=1.5.0
Requires-Dist: streamlit>=1.52.0
Provides-Extra: all
Requires-Dist: great-expectations>=0.18.0; extra == 'all'
Requires-Dist: orjson>=3.9.0; extra == 'all'
Requires-Dist: pandera>=0.18.0; extra == 'all'
Requires-Dist: plotly>=5.0.0; extra == 'all'
Requires-Dist: psycopg2-binary>=2.9.0; extra == 'all'
Requires-Dist: pyarrow>=14.0.0; extra == 'all'
Requires-Dist: pyod>=1.1.0; extra == 'all'
Requires-Dist: python-dotenv>=1.0.0; extra == 'all'
Requires-Dist: rich>=13.0.0; extra == 'all'
Requires-Dist: ruptures>=1.1.0; extra == 'all'
Requires-Dist: scikit-learn>=1.0.0; extra == 'all'
Requires-Dist: scipy>=1.10.0; extra == 'all'
Requires-Dist: sqlalchemy>=2.0.0; extra == 'all'
Requires-Dist: statsmodels>=0.14.0; extra == 'all'
Requires-Dist: streamlit-extras>=0.3.0; extra == 'all'
Requires-Dist: tsfresh>=0.20.0; extra == 'all'
Requires-Dist: typer>=0.9.0; extra == 'all'
Requires-Dist: ydata-profiling>=4.5.0; extra == 'all'
Provides-Extra: cli
Requires-Dist: python-dotenv>=1.0.0; extra == 'cli'
Requires-Dist: rich>=13.0.0; extra == 'cli'
Requires-Dist: typer>=0.9.0; extra == 'cli'
Provides-Extra: database
Requires-Dist: psycopg2-binary>=2.9.0; extra == 'database'
Requires-Dist: sqlalchemy>=2.0.0; extra == 'database'
Provides-Extra: dev
Requires-Dist: black>=23.0.0; extra == 'dev'
Requires-Dist: faker>=20.0.0; extra == 'dev'
Requires-Dist: hypothesis>=6.0.0; extra == 'dev'
Requires-Dist: mypy>=1.0.0; extra == 'dev'
Requires-Dist: pytest-cov>=4.0.0; extra == 'dev'
Requires-Dist: pytest>=7.0.0; extra == 'dev'
Requires-Dist: ruff>=0.1.0; extra == 'dev'
Provides-Extra: great-expectations
Requires-Dist: great-expectations>=0.18.0; extra == 'great-expectations'
Provides-Extra: ml
Requires-Dist: pyod>=1.1.0; extra == 'ml'
Requires-Dist: scikit-learn>=1.0.0; extra == 'ml'
Provides-Extra: pandera
Requires-Dist: pandera>=0.18.0; extra == 'pandera'
Provides-Extra: parquet
Requires-Dist: pyarrow>=14.0.0; extra == 'parquet'
Provides-Extra: plotly
Requires-Dist: plotly>=5.0.0; extra == 'plotly'
Provides-Extra: polars
Requires-Dist: polars>=0.19.0; extra == 'polars'
Provides-Extra: profiling
Requires-Dist: ydata-profiling>=4.5.0; extra == 'profiling'
Provides-Extra: stats
Requires-Dist: scipy>=1.10.0; extra == 'stats'
Provides-Extra: timeseries
Requires-Dist: ruptures>=1.1.0; extra == 'timeseries'
Requires-Dist: statsmodels>=0.14.0; extra == 'timeseries'
Requires-Dist: tsfresh>=0.20.0; extra == 'timeseries'
Provides-Extra: ui
Requires-Dist: streamlit-extras>=0.3.0; extra == 'ui'
